{
  "tarih": "2026-05-26",
  "guncelleme": "14:39",
  "karli_saatler": [
    "00",
    "01",
    "02",
    "03",
    "04",
    "05",
    "06",
    "07",
    "08",
    "09",
    "10",
    "11",
    "12",
    "13",
    "14",
    "15",
    "16",
    "17",
    "18",
    "19",
    "20",
    "21",
    "22",
    "23"
  ],
  "zararli_saatler": [],
  "btc_try": 3539931.0,
  "btc_usd": 77427.0,
  "gunluk_btc": 0.00339304,
  "gunluk_kar_tl": 8933.13,
  "gunluk_maliyet_tl": 3077.99,
  "ptf_saatlik": [
    199.99,
    175,
    171.01,
    174.99,
    171.01,
    171,
    0,
    0,
    0,
    0,
    0,
    0,
    0,
    0,
    0,
    0,
    0,
    0,
    19.99,
    190.01,
    328.01,
    315.01,
    296,
    175
  ]
}